LICENSE
README.md
scikit_decide-1.0.2.dist-info/RECORD
scikit_decide-1.0.2.dist-info/LICENSE
scikit_decide-1.0.2.dist-info/WHEEL
scikit_decide-1.0.2.dist-info/entry_points.txt
scikit_decide-1.0.2.dist-info/METADATA
skdecide/domains.py
skdecide/__init__.py
skdecide/core.py
skdecide/solvers.py
skdecide/optuna_utils.py
skdecide/utils.py
skdecide/parallel_domains.py
skdecide/builders/__init__.py
skdecide/builders/solver/assessability.py
skdecide/builders/solver/restorability.py
skdecide/builders/solver/parallelability.py
skdecide/builders/solver/policy.py
skdecide/builders/solver/__init__.py
skdecide/builders/solver/fromanystatesolvability.py
skdecide/builders/domain/memory.py
skdecide/builders/domain/goals.py
skdecide/builders/domain/events.py
skdecide/builders/domain/concurrency.py
skdecide/builders/domain/__init__.py
skdecide/builders/domain/observability.py
skdecide/builders/domain/initialization.py
skdecide/builders/domain/agent.py
skdecide/builders/domain/constraints.py
skdecide/builders/domain/value.py
skdecide/builders/domain/renderability.py
skdecide/builders/domain/dynamics.py
skdecide/builders/domain/scheduling/resource_consumption.py
skdecide/builders/domain/scheduling/task_duration.py
skdecide/builders/domain/scheduling/task.py
skdecide/builders/domain/scheduling/scheduling_domains.py
skdecide/builders/domain/scheduling/resource_availability.py
skdecide/builders/domain/scheduling/conditional_tasks.py
skdecide/builders/domain/scheduling/skills.py
skdecide/builders/domain/scheduling/time_windows.py
skdecide/builders/domain/scheduling/resource_costs.py
skdecide/builders/domain/scheduling/__init__.py
skdecide/builders/domain/scheduling/time_lag.py
skdecide/builders/domain/scheduling/graph_toolbox.py
skdecide/builders/domain/scheduling/modes.py
skdecide/builders/domain/scheduling/task_progress.py
skdecide/builders/domain/scheduling/preemptivity.py
skdecide/builders/domain/scheduling/resource_type.py
skdecide/builders/domain/scheduling/resource_renewability.py
skdecide/builders/domain/scheduling/scheduling_domains_modelling.py
skdecide/builders/domain/scheduling/preallocations.py
